mvmedia/__init__.py
mvmedia/move.py
mvmedia/parser.py
mvmedia/pathutil.py
mvmedia-1.0.1.dist-info/LICENSE.txt
mvmedia-1.0.1.dist-info/METADATA
mvmedia-1.0.1.dist-info/WHEEL
mvmedia-1.0.1.dist-info/entry_points.txt
mvmedia-1.0.1.dist-info/top_level.txt
mvmedia-1.0.1.dist-info/RECORD
