Metadata-Version: 2.1
Name: mvmedia
Version: 1.0.1
Summary: Safely move photos and videos
Home-page: https://github.com/samiconductor/mvmedia
Author: Sam Simmons
Author-email: sam@samiconductor.com
License: MIT
Project-URL: Source, https://github.com/samiconductor/mvmedia
Keywords: cli media
Platform: UNKNOWN
Classifier: Development Status :: 3 - Alpha
Classifier: License :: OSI Approved :: MIT License
Classifier: Operating System :: Unix
Classifier: Intended Audience :: System Administrators
Classifier: Programming Language :: Python :: 3 :: Only
Classifier: Topic :: Utilities
Classifier: Topic :: System :: Systems Administration
Requires-Python: >=3.4
Requires-Dist: exifread
Requires-Dist: python-magic
Provides-Extra: dev
Requires-Dist: readme-renderer ; extra == 'dev'
Requires-Dist: twine ; extra == 'dev'
Requires-Dist: wheel ; extra == 'dev'
